easyutils/__init__.py
easyutils/stock.py
easyutils/timeutils.py
easyutils-0.0.2.dist-info/DESCRIPTION.rst
easyutils-0.0.2.dist-info/METADATA
easyutils-0.0.2.dist-info/RECORD
easyutils-0.0.2.dist-info/WHEEL
easyutils-0.0.2.dist-info/metadata.json
easyutils-0.0.2.dist-info/top_level.txt
