Metadata-Version: 1.1
Name: easyutils
Version: 0.0.2
Summary: A utility for China Stock
Home-page: https://github.com/shidenggui/easyutils
Author: shidenggui
Author-email: longlyshidenggui@gmail.com
License: BSD
Keywords: China stock trade
Platform: UNKNOWN
Classifier: Development Status :: 4 - Beta
Classifier: Programming Language :: Python :: 2.7
Classifier: Programming Language :: Python :: 3.4
Classifier: Programming Language :: Python :: 3.5
Classifier: License :: OSI Approved :: BSD License
